mmproteo/__init__.py
mmproteo/__main__.py
mmproteo/_version.py
mmproteo/mmproteo.py
mmproteo/utils/__init__.py
mmproteo/utils/commands.py
mmproteo/utils/config.py
mmproteo/utils/download.py
mmproteo/utils/filters.py
mmproteo/utils/log.py
mmproteo/utils/paths.py
mmproteo/utils/pride.py
mmproteo/utils/processing.py
mmproteo/utils/utils.py
mmproteo/utils/visualization.py
mmproteo/utils/formats/__init__.py
mmproteo/utils/formats/archives.py
mmproteo/utils/formats/mgf.py
mmproteo/utils/formats/mz.py
mmproteo/utils/formats/raw.py
mmproteo/utils/formats/read.py
mmproteo/utils/formats/tf_dataset.py
mmproteo/utils/ml/__init__.py
mmproteo/utils/ml/callbacks.py
mmproteo/utils/ml/evaluation.py
mmproteo/utils/ml/layers.py
mmproteo/utils/ml/losses.py
mmproteo-0.8.3.dist-info/LICENSE
mmproteo-0.8.3.dist-info/METADATA
mmproteo-0.8.3.dist-info/WHEEL
mmproteo-0.8.3.dist-info/entry_points.txt
mmproteo-0.8.3.dist-info/top_level.txt
mmproteo-0.8.3.dist-info/RECORD
