Metadata-Version: 2.1
Name: mmproteo
Version: 0.8.3
Summary: Mirko meets Proteomics: A PRIDE Archive downloader and file converter
Home-page: https://github.com/Miroka96/mmproteo
Author: Mirko Krause
Author-email: krause@codebase.one
License: GPLv3+
Platform: UNKNOWN
Classifier: Programming Language :: Python :: 3
Classifier: Environment :: Console
Classifier: License :: OSI Approved :: GNU General Public License v3 or later (GPLv3+)
Classifier: Operating System :: OS Independent
Requires-Python: >=3.6
License-File: LICENSE
Requires-Dist: requests
Requires-Dist: pandas
Requires-Dist: pyteomics
Requires-Dist: wget
Requires-Dist: pyarrow
Requires-Dist: lxml
Requires-Dist: numpy
